python_prom_client/__init__.py
python_prom_client/prom_client_sc.py
prom_client_sc-0.2.dist-info/METADATA
prom_client_sc-0.2.dist-info/WHEEL
prom_client_sc-0.2.dist-info/top_level.txt
prom_client_sc-0.2.dist-info/RECORD
