Metadata-Version: 2.1
Name: prom-client-sc
Version: 0.2
Summary: Python wrapper for prometheus client
Home-page: https://github.com/ShareChat/python-prometheus-client
Author: Sanket
Author-email: souravmaitra@sharechat.co
License: UNKNOWN
Platform: UNKNOWN
Requires-Dist: prometheus-client
